{
  "schema": 1,
  "max_keep": 5,
  "versions": [
    {
      "id": "2026052911",
      "tag": "v2026052911",
      "published_at": "2026-05-29T17:46:33Z"
    },
    {
      "id": "2026052910",
      "tag": "v2026052910",
      "published_at": "2026-05-29T17:40:59Z"
    },
    {
      "id": "2026052909",
      "tag": "v2026052909",
      "published_at": "2026-05-29T17:17:43Z"
    },
    {
      "id": "2026052908",
      "tag": "v2026052908",
      "published_at": "2026-05-29T17:07:27Z"
    },
    {
      "id": "2026052907",
      "tag": "v2026052907",
      "published_at": "2026-05-29T16:59:43Z"
    }
  ]
}
