{
  "schema": 1,
  "max_keep": 5,
  "versions": [
    {
      "id": "2026060907",
      "tag": "v2026060907",
      "published_at": "2026-06-09T18:25:18Z",
      "summary": "优化 ocserv 组管理添加/编辑表单的排版与列表展示。"
    },
    {
      "id": "2026060906",
      "tag": "v2026060906",
      "published_at": "2026-06-09T18:04:40Z",
      "summary": "ocserv 组管理支持可选是否写入 select-group 列表，未选中时仅生成 config-per-group 配置文件。"
    },
    {
      "id": "2026060905",
      "tag": "v2026060905",
      "published_at": "2026-06-09T17:44:39Z",
      "summary": "修复 RADIUS 未启用 groupconfig 时组 API 仍拒绝编辑的问题。"
    },
    {
      "id": "2026060904",
      "tag": "v2026060904",
      "published_at": "2026-06-09T17:24:48Z",
      "summary": "修复多 WAN 出站策略表 default 路由无法下发，导致匹配源网段仍走主 WAN 的问题。"
    },
    {
      "id": "2026060903",
      "tag": "v2026060903",
      "published_at": "2026-06-09T17:02:34Z",
      "summary": "修复 ocserv RADIUS 未启用 groupconfig 时的本地组配置、多 WAN 策略路由出站与组配置文件命名。"
    }
  ]
}
